pldag/__init__.py
pldag/solver/__init__.py
pldag/solver/default_solver.py
pldag-0.10.17.dist-info/LICENSE
pldag-0.10.17.dist-info/METADATA
pldag-0.10.17.dist-info/WHEEL
pldag-0.10.17.dist-info/RECORD
