Metadata-Version: 2.1
Name: pldag
Version: 0.10.17
Summary: 
Author: znittzel
Author-email: rikard@ourstudio.se
Requires-Python: >=3.10,<4.0
Classifier: Programming Language :: Python :: 3
Classifier: Programming Language :: Python :: 3.10
Classifier: Programming Language :: Python :: 3.11
Classifier: Programming Language :: Python :: 3.12
Classifier: Programming Language :: Python :: 3.13
Provides-Extra: cvx
Requires-Dist: more-itertools (>=10.7.0,<11.0.0)
Requires-Dist: npycvx (>=0.0.4,<0.0.5) ; extra == "cvx"
Requires-Dist: numpy (>=2.1.2,<3.0.0)
